Metadata-Version: 2.1
Name: breame
Version: 0.1.2
Summary: Breame is a lightweight Python package with a number of tools to aid in the detection of words that have dual spellings and meanings in British and American English.
Home-page: https://github.com/cdpierse/breame
Author: Charles Pierse
Author-email: charlespierse@gmail.com
License: Apache-2.0
Keywords: text processing,natural language proessing,utility library,spelling,search engine
Platform: UNKNOWN
Classifier: Development Status :: 3 - Alpha
Classifier: Intended Audience :: Developers
Classifier: Topic :: Software Development :: Libraries :: Python Modules
Classifier: Programming Language :: Python :: 3.8
